HLrainflow/__init__.py
HLrainflow/rainflow.py
hlrainflow-0.0.5.dist-info/licenses/LICENSE
hlrainflow-0.0.5.dist-info/METADATA
hlrainflow-0.0.5.dist-info/WHEEL
hlrainflow-0.0.5.dist-info/top_level.txt
hlrainflow-0.0.5.dist-info/RECORD
