Metadata-Version: 2.4
Name: HLrainflow
Version: 0.0.5
Summary: A simple and efficient implementation of the Rainflow counting algorithm for fatigue analysis in Python.
Home-page: https://github.com/ShinsukeSakai0321/HLrainflow
Author: Shinsuke Sakai
Author-email: sakaishin0321@gmail.com
License: MIT
Classifier: Programming Language :: Python :: 3
Classifier: License :: OSI Approved :: MIT License
Classifier: Operating System :: OS Independent
Requires-Python: >=3.6
License-File: LICENSE
Requires-Dist: numpy==1.26.4
Dynamic: author
Dynamic: author-email
Dynamic: classifier
Dynamic: description
Dynamic: description-content-type
Dynamic: home-page
Dynamic: license
Dynamic: license-file
Dynamic: requires-dist
Dynamic: requires-python
Dynamic: summary
